odoo/addons/invader_payment_adyen/README.rst
odoo/addons/invader_payment_adyen/__init__.py
odoo/addons/invader_payment_adyen/__manifest__.py
odoo/addons/invader_payment_adyen/data/decimal_precision.xml
odoo/addons/invader_payment_adyen/i18n/invader_payment_adyen.pot
odoo/addons/invader_payment_adyen/models/__init__.py
odoo/addons/invader_payment_adyen/models/invader_payable.py
odoo/addons/invader_payment_adyen/models/payment_acquirer.py
odoo/addons/invader_payment_adyen/models/payment_transaction.py
odoo/addons/invader_payment_adyen/readme/CONFIGURE.rst
odoo/addons/invader_payment_adyen/readme/CONTRIBUTORS.rst
odoo/addons/invader_payment_adyen/readme/DESCRIPTION.rst
odoo/addons/invader_payment_adyen/readme/HISTORY.rst
odoo/addons/invader_payment_adyen/readme/USAGE.rst
odoo/addons/invader_payment_adyen/services/__init__.py
odoo/addons/invader_payment_adyen/services/exceptions.py
odoo/addons/invader_payment_adyen/services/invader_payment.py
odoo/addons/invader_payment_adyen/services/payment_adyen.py
odoo/addons/invader_payment_adyen/static/description/icon.png
odoo/addons/invader_payment_adyen/static/description/index.html
odoo/addons/invader_payment_adyen/views/payment_acquirer.xml
odoo/addons/invader_payment_adyen/views/payment_transaction.xml
odoo14_addon_invader_payment_adyen-14.0.1.0.5.dist-info/METADATA
odoo14_addon_invader_payment_adyen-14.0.1.0.5.dist-info/WHEEL
odoo14_addon_invader_payment_adyen-14.0.1.0.5.dist-info/top_level.txt
odoo14_addon_invader_payment_adyen-14.0.1.0.5.dist-info/RECORD
